pyingraph/PyG_graph_load.py
pyingraph/PyG_node_interface.py
pyingraph/__init__.py
pyingraph/examples_utils.py
pyingraph/graph_schema.json
pyingraph/examples/demo_control_system.py
pyingraph/examples/demo_simple_add.py
pyingraph/examples/graph_simple_demo.json
pyingraph/examples/pyingraph_export.json
pyingraph/examples/local_modules/mod_sink_print.py
pyingraph/examples/local_modules/mod_source_constant.py
pyingraph/examples/local_modules/mod_summer.py
pyingraph-0.2.0.dist-info/licenses/LICENSE
pyingraph-0.2.0.dist-info/METADATA
pyingraph-0.2.0.dist-info/WHEEL
pyingraph-0.2.0.dist-info/top_level.txt
pyingraph-0.2.0.dist-info/RECORD
